{
  "anchors": [
    { "anchor": "3 Rivers Logistics, Inc", "notes": "Font: Arial" },
    { "anchor": "68 Freight", "notes": "Font: Segoe UI" },
    { "anchor": "A. Duie Pyle Brokerage", "notes": "Font: Courier Std" },
    { "anchor": "A2B Cargo Logistics", "notes": "Arial" },
    { "anchor": "AG NEEDS LOGISTICS" },
    { "anchor": "AJC Logistics", "notes": "Time New Roman" },
    { "anchor": "Alamosatx", "notes": "email; Nimbus Sans" },
    { "anchor": "Alliance Shippers", "notes": "DejaVu Sans; Liberation Sans" },
    { "anchor": "AM TRANS EXPEDITE", "notes": "Courier New / Consolas" },
    { "anchor": "ANTLE MARKETING", "notes": "Calibri" },
    { "anchor": "Arlnetwork", "notes": "email; Arial" },
    { "anchor": "ARPCO TRANSPORT SERVICES", "notes": "Helvatica" },
    { "anchor": "ASAP LOGISTICS" },
    { "anchor": "ASM", "notes": "Bill to" },
    { "anchor": "CARGO CONVOY" },
    { "anchor": "Flat World OTR" },
    { "anchor": "Freight Trac Services" },
    { "anchor": "Global Transport" },
    { "anchor": "HARDINGER BROKERAGE" },
    { "anchor": "Hoffman Logistics" },
    { "anchor": "hoplite", "notes": "email; Roboto" },
    { "anchor": "KOND" },
    { "anchor": "Lange Logistics" },
    { "anchor": "MGM EXPRESS" },
    { "anchor": "MVP Worldwide Logistics" },
    { "anchor": "MYLES ENTERPRISES" },
    { "anchor": "Northwest Transportation" },
    { "anchor": "P.C.B" },
    { "anchor": "Planet Freight Inc" },
    { "anchor": "Sprint Logistics, LLC" },
    { "anchor": "AMERIGO LOGISTICS LLC", "notes": "Nimbus Sans" },
    { "anchor": "PRIORITY TRANSPORTATION INC" },
    { "anchor": "CCS Logistics" },
    { "anchor": "CBR Brokerage, Inc." },
    { "anchor": "AMERICAN FREIGHT MOVERS INC", "notes": "bottom right" },
    { "anchor": "C.A.T. Global Inc." },
    { "anchor": "Lightning Logistics Group" },
    { "anchor": "AIT Truckload Solutions" },
    { "anchor": "4G LOGISTICS LLC" },
    { "anchor": "ALG Direct, Inc." },
    { "anchor": "MonMel Logistics" },
    { "anchor": "Heyl Logistics LLC" },
    { "anchor": "ADVIK INC.", "notes": "bottom in terms and conditions" },
    { "anchor": "Maverick Logistics LLC" },
    { "anchor": "DHL Freight" },
    { "anchor": "Commodity Distribution, Inc" },
    { "anchor": "AMX logistics" },
    { "anchor": "WHY Logistics" },
    { "anchor": "ALPHACO LOGISTICS, INC.", "notes": "bottom right" },
    { "anchor": "ADEN LOGISTICS CORP" },
    { "anchor": "Blue Steel Courier Services" },
    { "anchor": "Advance Global Logistics" },
    { "anchor": "CB Logistics Group" },
    { "anchor": "Apple Express, Inc.", "notes": "bottom right" },
    { "anchor": "KNL Logistics LLC" },
    { "anchor": "Supply Chain Solutions" },
    { "anchor": "Real Matter" },
    { "anchor": "ARK LOGISTICS, LLC" },
    { "anchor": "@amistadfreight", "notes": "email" },
    { "anchor": "MVT Logistics, LLC" },
    { "anchor": "@ats-inc.com", "notes": "email; Courier New" },
    { "anchor": "ATS - Advance Transportation Systems" },
    { "anchor": "Pony Xpress Logistics" },
    { "anchor": "AIRPORT FREIGHT X-CHANGE" },
    { "anchor": "@challenger.com", "notes": "email" },
    { "anchor": "PRIDE TRANSPORT" },
    { "anchor": "LH Express LLC" },
    { "anchor": "AKI Logistics" },
    { "anchor": "L.J.Rogers Logistics" },
    { "anchor": "@forwardair.com", "notes": "email" },
    { "anchor": "Bendix Transportation, Inc." },
    { "anchor": "4WRD FREIGHT & LOGISTICS", "notes": "bottom right" },
    { "anchor": "Triple R Transportation LLC" },
    { "anchor": "G&T TRANSPORT 760 INC" },
    { "anchor": "Fortus Group Inc" },
    { "anchor": "TYGER LOGISTICS" },
    { "anchor": "AGX Freight" },
    { "anchor": "@10roadslogistics.com", "notes": "email" },
    { "anchor": "ACLogistics LLC" },
    { "anchor": "AMW EXPRESS LLC" },
    { "anchor": "ADM LOGISTICS, INC." },
    { "anchor": "IDAHO TRUCK SERVICE, INC" },
    { "anchor": "ACTION ENTERPRISE LOGISTICS", "notes": "SCALED DOWN clusterfuck" },
    { "anchor": "Creative Transportation Services, Inc." },
    { "anchor": "ANDOVER LOGISTICS LLC" },
    { "anchor": "MDS Logistics" },
    { "anchor": "RWB Trucking" },
    { "anchor": "AGFORCE TRANSPORT SERVICES" },
    { "anchor": "AAA Freight Global Inc" },
    { "anchor": "CCS Logistics" },
    { "anchor": "@aandztrucking.com", "notes": "email" },
    { "anchor": "White Shark Logistics" },
    { "anchor": "Pump Cargo" },
    { "anchor": "@gogriffith.com", "notes": "email" },
    { "anchor": "5K Logistics and Warehousing" },
    { "anchor": "Loadanza" },
    { "anchor": "AMERICAN LOGISTICS GROUP" },
    { "anchor": "7 Star Brokerage" },
    { "anchor": "TruPoint Logistics" },
    { "anchor": "CapLink Logistics, Inc." }
  ]
}
